{
  "icao": "OMDB",
  "label": "Dubai desert, afternoon",
  "capturedAt": "2026-06-29T09:26:21.702Z",
  "metar": {
    "icaoId": "OMDB",
    "receiptTime": "2026-06-29T09:00:47.242Z",
    "obsTime": 1782723600,
    "reportTime": "2026-06-29T09:00:00.000Z",
    "temp": 39,
    "dewp": 21,
    "wdir": 300,
    "wspd": 11,
    "visib": "6+",
    "altim": 999,
    "qcField": 16,
    "metarType": "METAR",
    "rawOb": "METAR OMDB 290900Z 30011KT 270V340 CAVOK 39/21 Q0999 NOSIG",
    "lat": 25.254,
    "lon": 55.366,
    "elev": 5,
    "name": "Dubai Intl, DU, AE",
    "cover": "CAVOK",
    "clouds": [],
    "fltCat": "VFR"
  },
  "om": {
    "latitude": 25.272406,
    "longitude": 55.36216,
    "generationtime_ms": 29.703378677368164,
    "utc_offset_seconds": 0,
    "timezone": "GMT",
    "timezone_abbreviation": "GMT",
    "elevation": 2,
    "hourly_units": {
      "time": "iso8601",
      "temperature_2m": "°C",
      "relative_humidity_2m": "%",
      "dew_point_2m": "°C",
      "wind_speed_10m": "kn",
      "wind_direction_10m": "°",
      "precipitation": "mm",
      "precipitation_probability": "%",
      "cloud_cover": "%",
      "cloud_cover_low": "%",
      "cloud_cover_mid": "%",
      "temperature_1000hPa": "°C",
      "relative_humidity_1000hPa": "%",
      "geopotential_height_1000hPa": "m",
      "cloud_cover_1000hPa": "%",
      "wind_speed_1000hPa": "kn",
      "wind_direction_1000hPa": "°",
      "temperature_975hPa": "°C",
      "relative_humidity_975hPa": "%",
      "geopotential_height_975hPa": "m",
      "cloud_cover_975hPa": "%",
      "wind_speed_975hPa": "kn",
      "wind_direction_975hPa": "°",
      "temperature_950hPa": "°C",
      "relative_humidity_950hPa": "%",
      "geopotential_height_950hPa": "m",
      "cloud_cover_950hPa": "%",
      "wind_speed_950hPa": "kn",
      "wind_direction_950hPa": "°",
      "temperature_925hPa": "°C",
      "relative_humidity_925hPa": "%",
      "geopotential_height_925hPa": "m",
      "cloud_cover_925hPa": "%",
      "wind_speed_925hPa": "kn",
      "wind_direction_925hPa": "°",
      "temperature_900hPa": "°C",
      "relative_humidity_900hPa": "%",
      "geopotential_height_900hPa": "m",
      "cloud_cover_900hPa": "%",
      "wind_speed_900hPa": "kn",
      "wind_direction_900hPa": "°",
      "temperature_850hPa": "°C",
      "relative_humidity_850hPa": "%",
      "geopotential_height_850hPa": "m",
      "cloud_cover_850hPa": "%",
      "wind_speed_850hPa": "kn",
      "wind_direction_850hPa": "°",
      "temperature_800hPa": "°C",
      "relative_humidity_800hPa": "%",
      "geopotential_height_800hPa": "m",
      "cloud_cover_800hPa": "%",
      "wind_speed_800hPa": "kn",
      "wind_direction_800hPa": "°",
      "temperature_700hPa": "°C",
      "relative_humidity_700hPa": "%",
      "geopotential_height_700hPa": "m",
      "cloud_cover_700hPa": "%",
      "wind_speed_700hPa": "kn",
      "wind_direction_700hPa": "°"
    },
    "hourly": {
      "time": [
        "2026-06-28T00:00",
        "2026-06-28T01:00",
        "2026-06-28T02:00",
        "2026-06-28T03:00",
        "2026-06-28T04:00",
        "2026-06-28T05:00",
        "2026-06-28T06:00",
        "2026-06-28T07:00",
        "2026-06-28T08:00",
        "2026-06-28T09:00",
        "2026-06-28T10:00",
        "2026-06-28T11:00",
        "2026-06-28T12:00",
        "2026-06-28T13:00",
        "2026-06-28T14:00",
        "2026-06-28T15:00",
        "2026-06-28T16:00",
        "2026-06-28T17:00",
        "2026-06-28T18:00",
        "2026-06-28T19:00",
        "2026-06-28T20:00",
        "2026-06-28T21:00",
        "2026-06-28T22:00",
        "2026-06-28T23:00",
        "2026-06-29T00:00",
        "2026-06-29T01:00",
        "2026-06-29T02:00",
        "2026-06-29T03:00",
        "2026-06-29T04:00",
        "2026-06-29T05:00",
        "2026-06-29T06:00",
        "2026-06-29T07:00",
        "2026-06-29T08:00",
        "2026-06-29T09:00",
        "2026-06-29T10:00",
        "2026-06-29T11:00",
        "2026-06-29T12:00",
        "2026-06-29T13:00",
        "2026-06-29T14:00",
        "2026-06-29T15:00",
        "2026-06-29T16:00",
        "2026-06-29T17:00",
        "2026-06-29T18:00",
        "2026-06-29T19:00",
        "2026-06-29T20:00",
        "2026-06-29T21:00",
        "2026-06-29T22:00",
        "2026-06-29T23:00"
      ],
      "temperature_2m": [
        31.8,
        31.4,
        31.3,
        32.2,
        33.9,
        36,
        38.1,
        39.3,
        38.8,
        38.3,
        37.9,
        37.3,
        37.1,
        35.7,
        34.6,
        33.8,
        33.3,
        33,
        32.6,
        32.1,
        31.9,
        31.6,
        31.2,
        30.9,
        31.5,
        30.9,
        31,
        32.1,
        33.5,
        36,
        38.4,
        39.5,
        38.5,
        38.1,
        37.3,
        36.3,
        35.7,
        35,
        34,
        33.1,
        32.5,
        32.1,
        31.8,
        31.6,
        31.3,
        30.8,
        30.4,
        30
      ],
      "relative_humidity_2m": [
        69,
        72,
        73,
        70,
        59,
        48,
        39,
        38,
        46,
        46,
        44,
        47,
        46,
        56,
        64,
        66,
        70,
        71,
        70,
        72,
        74,
        74,
        76,
        77,
        72,
        73,
        75,
        66,
        55,
        41,
        30,
        27,
        36,
        34,
        40,
        48,
        50,
        55,
        59,
        65,
        71,
        73,
        73,
        72,
        75,
        79,
        81,
        84
      ],
      "dew_point_2m": [
        25.5,
        25.7,
        26,
        26,
        24.8,
        23.2,
        21.9,
        22.3,
        25.2,
        24.8,
        23.5,
        24.1,
        23.7,
        25.6,
        26.7,
        26.6,
        27.1,
        27,
        26.4,
        26.5,
        26.6,
        26.5,
        26.4,
        26.4,
        25.9,
        25.6,
        25.9,
        24.8,
        23.3,
        20.7,
        17.7,
        17.1,
        20.7,
        19.5,
        21.4,
        23.6,
        23.8,
        24.5,
        24.9,
        25.6,
        26.4,
        26.7,
        26.3,
        26.1,
        26.4,
        26.6,
        26.7,
        27
      ],
      "wind_speed_10m": [
        2.2,
        2.7,
        3.6,
        4.2,
        4.8,
        4.9,
        3.8,
        3,
        6.7,
        8.4,
        8.7,
        7.4,
        7.5,
        6.7,
        6.3,
        4.7,
        4.1,
        2.8,
        3.7,
        3.2,
        3.5,
        2.7,
        2.1,
        1.9,
        2.6,
        1.4,
        0.1,
        1.9,
        3.2,
        2.8,
        2.2,
        4.2,
        6.6,
        7.3,
        7.2,
        6.6,
        5.7,
        4.9,
        4.2,
        3.6,
        3.6,
        3.4,
        3.5,
        3.6,
        2.8,
        3.8,
        4.3,
        4.2
      ],
      "wind_direction_10m": [
        2,
        30,
        47,
        50,
        61,
        70,
        59,
        6,
        338,
        339,
        335,
        333,
        334,
        323,
        325,
        326,
        318,
        301,
        285,
        282,
        300,
        308,
        321,
        336,
        333,
        335,
        180,
        139,
        145,
        158,
        221,
        282,
        294,
        289,
        286,
        289,
        288,
        284,
        285,
        268,
        232,
        226,
        208,
        221,
        211,
        190,
        194,
        189
      ],
      "precipitation": [
        0,
        0,
        0,
        0,
        0,
        0,
        0,
        0,
        0,
        0,
        0,
        0,
        0,
        0,
        0,
        0,
        0,
        0,
        0,
        0,
        0,
        0,
        0,
        0,
        0,
        0,
        0,
        0,
        0,
        0,
        0,
        0,
        0,
        0,
        0,
        0,
        0,
        0,
        0,
        0,
        0,
        0,
        0,
        0,
        0,
        0,
        0,
        0
      ],
      "precipitation_probability": [
        0,
        0,
        0,
        0,
        0,
        0,
        0,
        0,
        0,
        0,
        1,
        2,
        2,
        2,
        1,
        0,
        0,
        0,
        0,
        0,
        0,
        0,
        0,
        0,
        0,
        0,
        0,
        0,
        0,
        0,
        0,
        0,
        0,
        0,
        0,
        0,
        0,
        0,
        0,
        0,
        0,
        0,
        0,
        0,
        0,
        0,
        0,
        0
      ],
      "cloud_cover": [
        0,
        0,
        0,
        0,
        0,
        0,
        0,
        0,
        0,
        0,
        16,
        19,
        14,
        6,
        4,
        9,
        5,
        3,
        2,
        0,
        0,
        0,
        0,
        0,
        0,
        0,
        0,
        4,
        4,
        0,
        0,
        0,
        0,
        0,
        0,
        1,
        1,
        2,
        2,
        2,
        1,
        0,
        0,
        0,
        33,
        20,
        15,
        14
      ],
      "cloud_cover_low": [
        0,
        0,
        0,
        0,
        0,
        0,
        0,
        0,
        0,
        0,
        0,
        0,
        0,
        0,
        0,
        0,
        0,
        0,
        0,
        0,
        0,
        0,
        0,
        0,
        0,
        0,
        0,
        0,
        0,
        0,
        0,
        0,
        0,
        0,
        0,
        0,
        0,
        0,
        0,
        0,
        0,
        0,
        0,
        0,
        0,
        0,
        0,
        0
      ],
      "cloud_cover_mid": [
        0,
        0,
        0,
        0,
        0,
        0,
        0,
        0,
        0,
        0,
        9,
        3,
        3,
        1,
        0,
        8,
        5,
        1,
        0,
        0,
        0,
        0,
        0,
        0,
        0,
        0,
        0,
        4,
        4,
        0,
        0,
        0,
        0,
        0,
        0,
        1,
        1,
        2,
        2,
        2,
        1,
        0,
        0,
        0,
        0,
        0,
        0,
        0
      ],
      "temperature_1000hPa": [
        31.6,
        31.5,
        31.4,
        31.6,
        32.6,
        33.9,
        35.5,
        36.9,
        38,
        37.7,
        36.3,
        36.4,
        35.8,
        35.2,
        34.6,
        33.4,
        32.8,
        32.5,
        32.6,
        32.4,
        32.1,
        31.9,
        31.7,
        31.5,
        31.5,
        31.3,
        31,
        31.1,
        32,
        33.7,
        35.7,
        37.5,
        37.8,
        36.8,
        36.2,
        35.6,
        35.3,
        34.7,
        34.2,
        33.7,
        33.1,
        32.9,
        32.7,
        32.4,
        32.2,
        32,
        31.8,
        31.6
      ],
      "relative_humidity_1000hPa": [
        76,
        76,
        75,
        72,
        64,
        55,
        51,
        47,
        44,
        51,
        59,
        54,
        57,
        60,
        60,
        75,
        77,
        74,
        71,
        72,
        72,
        74,
        76,
        79,
        79,
        80,
        81,
        80,
        71,
        57,
        43,
        34,
        36,
        45,
        50,
        51,
        52,
        61,
        62,
        64,
        68,
        66,
        65,
        67,
        70,
        72,
        72,
        73
      ],
      "geopotential_height_1000hPa": [
        0,
        -3,
        2,
        6,
        14,
        14,
        13,
        8,
        6,
        5,
        4,
        -2,
        -6,
        -10,
        -10,
        -13,
        -9,
        -5,
        1,
        1,
        -1,
        -3,
        -4,
        -6,
        -9,
        -9,
        -6,
        -4,
        1,
        1,
        0,
        -6,
        -11,
        -13,
        -15,
        -18,
        -21,
        -24,
        -24,
        -23,
        -21,
        -17,
        -13,
        -14,
        -18,
        -21,
        -26,
        -27
      ],
      "cloud_cover_1000hPa": [
        0,
        0,
        0,
        0,
        0,
        0,
        0,
        0,
        0,
        0,
        0,
        0,
        0,
        0,
        0,
        0,
        0,
        0,
        0,
        0,
        0,
        0,
        0,
        0,
        0,
        0,
        0,
        0,
        0,
        0,
        0,
        0,
        0,
        0,
        0,
        0,
        0,
        0,
        0,
        0,
        0,
        0,
        0,
        0,
        0,
        0,
        0,
        0
      ],
      "wind_speed_1000hPa": [
        2.5,
        2.8,
        2.9,
        3.5,
        4.4,
        4.1,
        2.1,
        1.6,
        3.7,
        7.6,
        8.5,
        8.6,
        8.2,
        7.5,
        6.7,
        5.9,
        4,
        2.6,
        2.4,
        3,
        2.9,
        2.5,
        2.1,
        1.4,
        1.2,
        0.2,
        1.7,
        2.2,
        2.6,
        2.9,
        2.4,
        3.7,
        6.1,
        7,
        7.3,
        7.4,
        7.4,
        6.6,
        5.2,
        4.5,
        3.3,
        2.3,
        2.4,
        2.6,
        2.5,
        2.5,
        3.5,
        3.8
      ],
      "wind_direction_1000hPa": [
        23,
        34,
        42,
        52,
        58,
        71,
        68,
        30,
        321,
        316,
        323,
        332,
        326,
        321,
        314,
        311,
        299,
        283,
        305,
        310,
        318,
        315,
        319,
        315,
        321,
        90,
        144,
        153,
        163,
        172,
        209,
        267,
        292,
        300,
        302,
        303,
        300,
        294,
        283,
        275,
        267,
        246,
        235,
        228,
        225,
        203,
        199,
        192
      ],
      "temperature_975hPa": [
        30.4,
        30.3,
        30.3,
        30.4,
        31,
        31.5,
        33,
        34.4,
        35.5,
        35.4,
        34.4,
        35,
        34.9,
        35,
        35.2,
        34.7,
        34.3,
        33.8,
        33.2,
        32.4,
        31.6,
        31.3,
        31.2,
        31.1,
        31,
        30.9,
        31,
        31.2,
        32.1,
        33.3,
        34.4,
        35.2,
        35.7,
        35.1,
        34.8,
        34.7,
        34.7,
        34.5,
        34.3,
        34.2,
        34.2,
        34.2,
        33.9,
        33.4,
        32.8,
        32.4,
        32.8,
        32.8
      ],
      "relative_humidity_975hPa": [
        71,
        72,
        71,
        68,
        62,
        62,
        58,
        54,
        50,
        56,
        62,
        54,
        48,
        43,
        39,
        46,
        47,
        48,
        50,
        55,
        59,
        62,
        62,
        62,
        62,
        62,
        61,
        58,
        50,
        41,
        34,
        38,
        39,
        40,
        39,
        38,
        38,
        40,
        40,
        42,
        42,
        41,
        42,
        46,
        52,
        54,
        50,
        50
      ],
      "geopotential_height_975hPa": [
        227.45,
        224.45,
        229.94,
        233.45,
        241.94,
        242.42,
        242.89,
        238.38,
        237.36,
        235.87,
        234.38,
        228.38,
        223.89,
        219.4,
        219.4,
        216.4,
        219.91,
        223.43,
        229.42,
        229.42,
        226.94,
        224.94,
        223.45,
        221.94,
        218.45,
        218.45,
        221.45,
        223.94,
        228.94,
        229.42,
        229.4,
        224.38,
        219.38,
        216.89,
        214.4,
        211.4,
        207.91,
        204.92,
        204.92,
        205.43,
        207.91,
        211.91,
        215.43,
        214.43,
        209.94,
        206.94,
        201.94,
        200.45
      ],
      "cloud_cover_975hPa": [
        0,
        0,
        0,
        0,
        0,
        0,
        0,
        0,
        0,
        0,
        0,
        0,
        0,
        0,
        0,
        0,
        0,
        0,
        0,
        0,
        0,
        0,
        0,
        0,
        0,
        0,
        0,
        0,
        0,
        0,
        0,
        0,
        0,
        0,
        0,
        0,
        0,
        0,
        0,
        0,
        0,
        0,
        0,
        0,
        0,
        0,
        0,
        0
      ],
      "wind_speed_975hPa": [
        4.6,
        5,
        5.3,
        5.9,
        6.5,
        5.8,
        2.6,
        1.7,
        2.6,
        5.5,
        7,
        7.7,
        8,
        6.9,
        6,
        5.7,
        4.1,
        3.4,
        3.4,
        3.8,
        4,
        3.8,
        3.7,
        3.6,
        3.9,
        2.7,
        1.3,
        0.4,
        1,
        1.9,
        2.6,
        3.7,
        6.3,
        7,
        7.3,
        7.5,
        8.1,
        8.1,
        7.7,
        7.5,
        6.8,
        6.5,
        6.7,
        7,
        6.4,
        5.4,
        6.1,
        6.3
      ],
      "wind_direction_975hPa": [
        47,
        54,
        60,
        68,
        76,
        79,
        79,
        53,
        331,
        320,
        328,
        332,
        329,
        327,
        319,
        314,
        300,
        278,
        296,
        298,
        307,
        306,
        309,
        311,
        320,
        329,
        329,
        282,
        222,
        214,
        237,
        265,
        289,
        298,
        301,
        299,
        293,
        289,
        281,
        280,
        278,
        274,
        272,
        270,
        270,
        263,
        257,
        252
      ],
      "temperature_950hPa": [
        29.3,
        29.1,
        29.2,
        29.3,
        29.5,
        29.2,
        30.5,
        31.8,
        33,
        33.2,
        32.6,
        33.6,
        33.9,
        34.9,
        35.7,
        36,
        35.7,
        35.1,
        33.7,
        32.5,
        31.2,
        30.7,
        30.7,
        30.7,
        30.4,
        30.5,
        31,
        31.4,
        32.2,
        33,
        33.2,
        33,
        33.5,
        33.3,
        33.3,
        33.8,
        34.2,
        34.3,
        34.4,
        34.8,
        35.2,
        35.4,
        35.1,
        34.4,
        33.3,
        32.8,
        33.7,
        34
      ],
      "relative_humidity_950hPa": [
        66,
        67,
        66,
        63,
        60,
        69,
        65,
        60,
        55,
        60,
        64,
        53,
        39,
        26,
        18,
        16,
        17,
        21,
        28,
        37,
        45,
        49,
        47,
        45,
        45,
        43,
        40,
        36,
        29,
        24,
        25,
        41,
        41,
        35,
        27,
        25,
        24,
        18,
        18,
        19,
        16,
        15,
        18,
        24,
        33,
        36,
        28,
        27
      ],
      "geopotential_height_950hPa": [
        460,
        457,
        463,
        466,
        475,
        476,
        478,
        474,
        474,
        472,
        470,
        464,
        459,
        454,
        454,
        451,
        454,
        457,
        463,
        463,
        460,
        458,
        456,
        455,
        451,
        451,
        454,
        457,
        462,
        463,
        464,
        460,
        455,
        452,
        449,
        446,
        442,
        439,
        439,
        439,
        442,
        446,
        449,
        448,
        443,
        440,
        435,
        433
      ],
      "cloud_cover_950hPa": [
        0,
        0,
        0,
        0,
        0,
        0,
        0,
        0,
        0,
        0,
        0,
        0,
        0,
        0,
        0,
        0,
        0,
        0,
        0,
        0,
        0,
        0,
        0,
        0,
        0,
        0,
        0,
        0,
        0,
        0,
        0,
        0,
        0,
        0,
        0,
        0,
        0,
        0,
        0,
        0,
        0,
        0,
        0,
        0,
        0,
        0,
        0,
        0
      ],
      "wind_speed_950hPa": [
        7.1,
        7.4,
        8,
        8.5,
        9,
        7.6,
        3.1,
        2,
        1.7,
        3.5,
        5.5,
        6.8,
        7.8,
        6.4,
        5.4,
        5.5,
        4.1,
        4.2,
        4.5,
        4.7,
        5.2,
        5.2,
        5.4,
        5.8,
        6.5,
        5.5,
        4.2,
        2.7,
        2.3,
        2.5,
        3.2,
        3.8,
        6.5,
        7,
        7.3,
        7.6,
        8.8,
        9.7,
        10.2,
        10.5,
        10.5,
        11,
        11.6,
        12.2,
        11.2,
        9.9,
        10.7,
        11.3
      ],
      "wind_direction_950hPa": [
        56,
        61,
        67,
        74,
        85,
        84,
        86,
        72,
        353,
        327,
        335,
        333,
        333,
        333,
        324,
        317,
        300,
        276,
        292,
        291,
        302,
        302,
        306,
        311,
        320,
        328,
        327,
        321,
        297,
        265,
        259,
        264,
        287,
        297,
        301,
        294,
        288,
        285,
        281,
        282,
        282,
        280,
        279,
        278,
        279,
        276,
        273,
        269
      ],
      "temperature_925hPa": [
        28.9,
        28.9,
        29,
        29.2,
        29.2,
        29.1,
        28.9,
        29.5,
        30.8,
        31.6,
        31.8,
        32.7,
        34.2,
        35.1,
        35.7,
        35.9,
        35.8,
        35.4,
        34.5,
        34,
        33.4,
        32.7,
        32.4,
        32,
        31.4,
        31.5,
        32,
        32.5,
        33.3,
        33.8,
        34.2,
        34.3,
        34.2,
        34.8,
        35.4,
        35.8,
        36,
        36.1,
        36.1,
        36.2,
        36.3,
        36.3,
        36.3,
        36.3,
        36,
        35.7,
        36,
        36.3
      ],
      "relative_humidity_925hPa": [
        67,
        66,
        63,
        59,
        59,
        63,
        71,
        67,
        61,
        60,
        60,
        49,
        19,
        10,
        8,
        10,
        13,
        18,
        26,
        26,
        27,
        28,
        30,
        32,
        29,
        26,
        21,
        18,
        15,
        12,
        9,
        9,
        8,
        7,
        6,
        6,
        5,
        6,
        7,
        8,
        8,
        9,
        9,
        9,
        11,
        13,
        12,
        11
      ],
      "geopotential_height_925hPa": [
        698,
        696,
        701,
        705,
        714,
        714,
        717,
        714,
        715,
        713,
        711,
        706,
        701,
        696,
        696,
        693,
        696,
        699,
        704,
        704,
        700,
        697,
        696,
        694,
        690,
        690,
        693,
        696,
        701,
        704,
        704,
        700,
        696,
        692,
        690,
        687,
        684,
        681,
        680,
        681,
        684,
        688,
        691,
        690,
        684,
        681,
        677,
        675
      ],
      "cloud_cover_925hPa": [
        0,
        0,
        0,
        0,
        0,
        0,
        0,
        0,
        0,
        0,
        0,
        0,
        0,
        0,
        0,
        0,
        0,
        0,
        0,
        0,
        0,
        0,
        0,
        0,
        0,
        0,
        0,
        0,
        0,
        0,
        0,
        0,
        0,
        0,
        0,
        0,
        0,
        0,
        0,
        0,
        0,
        0,
        0,
        0,
        0,
        0,
        0,
        0
      ],
      "wind_speed_925hPa": [
        7.6,
        7.8,
        8,
        8.5,
        8.9,
        9,
        5.6,
        2.6,
        1.2,
        1.2,
        0.7,
        2,
        3.1,
        2.6,
        2.2,
        2.3,
        1.9,
        3.1,
        3.1,
        3.8,
        4.5,
        5.3,
        5.6,
        5.9,
        7.2,
        6.9,
        7,
        6.8,
        7.2,
        7.8,
        8.5,
        8.3,
        8,
        7.9,
        8.5,
        9.7,
        10.7,
        10.8,
        10,
        10,
        10.4,
        11.2,
        12,
        13.7,
        14.6,
        15,
        16.2,
        16.7
      ],
      "wind_direction_925hPa": [
        92,
        93,
        93,
        93,
        96,
        105,
        126,
        90,
        68,
        112,
        90,
        319,
        304,
        312,
        299,
        287,
        243,
        219,
        219,
        223,
        231,
        235,
        242,
        253,
        277,
        283,
        284,
        279,
        275,
        272,
        273,
        276,
        281,
        279,
        277,
        280,
        288,
        292,
        292,
        290,
        290,
        288,
        287,
        285,
        288,
        294,
        298,
        300
      ],
      "temperature_900hPa": [
        28.6,
        28.5,
        28.5,
        28.3,
        28.3,
        28.5,
        28.6,
        28.6,
        29,
        29.7,
        30.3,
        31.6,
        33,
        33.2,
        33.3,
        33.3,
        33.2,
        33,
        32.4,
        32.1,
        31.7,
        31.5,
        31.4,
        31.3,
        31.5,
        31.6,
        32,
        32.3,
        32.7,
        33.2,
        33.4,
        33.6,
        33.9,
        34.1,
        34.3,
        34.8,
        35.1,
        35.3,
        35.3,
        35.3,
        35.2,
        35.3,
        35.5,
        35.5,
        35.3,
        35.1,
        35.2,
        35.5
      ],
      "relative_humidity_900hPa": [
        64,
        65,
        66,
        66,
        64,
        62,
        63,
        63,
        63,
        64,
        56,
        38,
        17,
        16,
        20,
        24,
        27,
        32,
        40,
        43,
        44,
        44,
        45,
        46,
        35,
        31,
        27,
        23,
        20,
        17,
        15,
        12,
        10,
        9,
        7,
        5,
        5,
        6,
        7,
        9,
        10,
        10,
        9,
        9,
        8,
        9,
        9,
        9
      ],
      "geopotential_height_900hPa": [
        943,
        940,
        946,
        949,
        958,
        959,
        961,
        959,
        960,
        960,
        958,
        953,
        948,
        943,
        944,
        940,
        944,
        947,
        952,
        951,
        947,
        944,
        942,
        940,
        936,
        936,
        939,
        942,
        948,
        950,
        951,
        947,
        943,
        940,
        938,
        935,
        932,
        929,
        928,
        929,
        932,
        936,
        939,
        938,
        933,
        929,
        925,
        924
      ],
      "cloud_cover_900hPa": [
        0,
        0,
        0,
        0,
        0,
        0,
        0,
        0,
        0,
        0,
        0,
        0,
        0,
        0,
        0,
        0,
        0,
        0,
        0,
        0,
        0,
        0,
        0,
        0,
        0,
        0,
        0,
        0,
        0,
        0,
        0,
        0,
        0,
        0,
        0,
        0,
        0,
        0,
        0,
        0,
        0,
        0,
        0,
        0,
        0,
        0,
        0,
        0
      ],
      "wind_speed_900hPa": [
        9.2,
        9.3,
        8.8,
        8.4,
        8.1,
        7.6,
        5.2,
        5.9,
        2.1,
        2.4,
        2.2,
        1.3,
        2,
        0.9,
        0.9,
        1.4,
        2.5,
        3.9,
        4.3,
        5,
        5.8,
        6.8,
        7.5,
        7.7,
        8.8,
        8.8,
        9.2,
        9.8,
        10.6,
        11.2,
        11.8,
        12.3,
        12.4,
        12,
        12.3,
        12.4,
        12.2,
        12,
        11,
        10.4,
        10.2,
        10.6,
        11.5,
        13.2,
        14.7,
        15.9,
        17.2,
        18.2
      ],
      "wind_direction_900hPa": [
        115,
        116,
        116,
        114,
        113,
        117,
        151,
        157,
        131,
        139,
        135,
        121,
        270,
        284,
        194,
        180,
        170,
        173,
        174,
        183,
        191,
        201,
        209,
        218,
        238,
        244,
        248,
        251,
        254,
        255,
        258,
        262,
        268,
        272,
        276,
        285,
        292,
        296,
        296,
        297,
        298,
        297,
        293,
        290,
        291,
        294,
        298,
        302
      ],
      "temperature_850hPa": [
        28,
        28.2,
        28.5,
        28.4,
        28.1,
        28,
        27.9,
        27.8,
        27.9,
        27.6,
        28.5,
        28.8,
        29.8,
        29.9,
        30.3,
        30.5,
        30.4,
        30.3,
        30.3,
        30.3,
        30.3,
        30.2,
        30.2,
        30.1,
        30.3,
        30.2,
        30.2,
        30.2,
        30.2,
        30.3,
        30.4,
        30.5,
        30.7,
        30.8,
        30.9,
        31.1,
        31.3,
        31.4,
        31.5,
        31.6,
        31.7,
        31.9,
        31.9,
        31.9,
        31.7,
        31.7,
        31.7,
        31.7
      ],
      "relative_humidity_850hPa": [
        33,
        30,
        27,
        26,
        26,
        25,
        20,
        18,
        16,
        22,
        23,
        28,
        15,
        18,
        18,
        17,
        19,
        22,
        21,
        22,
        21,
        22,
        22,
        22,
        17,
        19,
        18,
        18,
        16,
        15,
        13,
        11,
        10,
        9,
        8,
        8,
        11,
        15,
        15,
        13,
        13,
        13,
        13,
        13,
        12,
        11,
        11,
        11
      ],
      "geopotential_height_850hPa": [
        1452,
        1449,
        1454,
        1458,
        1467,
        1467,
        1470,
        1467,
        1468,
        1468,
        1467,
        1463,
        1459,
        1455,
        1456,
        1453,
        1456,
        1460,
        1464,
        1464,
        1460,
        1456,
        1454,
        1452,
        1447,
        1447,
        1450,
        1454,
        1460,
        1462,
        1463,
        1459,
        1455,
        1452,
        1450,
        1448,
        1445,
        1443,
        1442,
        1444,
        1446,
        1451,
        1454,
        1452,
        1447,
        1443,
        1439,
        1438
      ],
      "cloud_cover_850hPa": [
        0,
        0,
        0,
        0,
        0,
        0,
        0,
        0,
        0,
        0,
        0,
        0,
        0,
        0,
        0,
        0,
        0,
        0,
        0,
        0,
        0,
        0,
        0,
        0,
        0,
        0,
        0,
        0,
        0,
        0,
        0,
        0,
        0,
        0,
        0,
        0,
        0,
        0,
        0,
        0,
        0,
        0,
        0,
        0,
        0,
        0,
        0,
        0
      ],
      "wind_speed_850hPa": [
        10.8,
        10.8,
        10.7,
        10.3,
        9.8,
        9.9,
        10.7,
        10,
        9.5,
        6.7,
        7,
        6.2,
        3.9,
        2.5,
        2.2,
        1.9,
        2.4,
        2.3,
        0.9,
        1.4,
        2.2,
        3.4,
        3.9,
        4.8,
        7.1,
        7.6,
        8,
        8.1,
        8.2,
        8,
        8,
        8.3,
        8.7,
        8.7,
        8.7,
        8.8,
        9.2,
        9.6,
        8.6,
        7.5,
        6.8,
        6.8,
        7.6,
        9,
        10.8,
        12.3,
        13.8,
        15.4
      ],
      "wind_direction_850hPa": [
        150,
        153,
        157,
        162,
        167,
        173,
        196,
        197,
        197,
        186,
        168,
        151,
        198,
        180,
        153,
        140,
        135,
        148,
        214,
        239,
        243,
        240,
        243,
        255,
        268,
        274,
        281,
        282,
        287,
        288,
        288,
        289,
        292,
        295,
        299,
        306,
        316,
        322,
        323,
        322,
        316,
        308,
        299,
        291,
        291,
        293,
        297,
        301
      ],
      "temperature_800hPa": [
        25.9,
        25.5,
        25.4,
        25,
        24.9,
        25,
        25,
        25.1,
        25.3,
        25.3,
        25.3,
        25.7,
        26.1,
        26.2,
        26.2,
        26.2,
        26.1,
        26.1,
        25.8,
        26.1,
        26.2,
        26.1,
        26.1,
        25.9,
        25.9,
        25.8,
        25.8,
        25.8,
        25.9,
        26.1,
        26.3,
        26.6,
        26.8,
        27,
        27,
        27.1,
        27.4,
        27.5,
        27.7,
        27.9,
        28.1,
        28.4,
        28.4,
        28.5,
        28.4,
        28.1,
        28.1,
        28
      ],
      "relative_humidity_800hPa": [
        15,
        18,
        21,
        22,
        23,
        22,
        18,
        19,
        20,
        25,
        30,
        28,
        27,
        25,
        24,
        24,
        24,
        24,
        24,
        21,
        20,
        20,
        20,
        20,
        19,
        19,
        19,
        18,
        17,
        15,
        12,
        11,
        10,
        9,
        9,
        10,
        11,
        12,
        13,
        13,
        13,
        14,
        15,
        15,
        16,
        16,
        16,
        15
      ],
      "geopotential_height_800hPa": [
        1987,
        1984,
        1989,
        1992,
        2000,
        2001,
        2003,
        2000,
        2001,
        2002,
        2002,
        1999,
        1995,
        1991,
        1993,
        1990,
        1994,
        1997,
        2001,
        2000,
        1996,
        1992,
        1990,
        1988,
        1984,
        1983,
        1986,
        1990,
        1996,
        1998,
        2000,
        1996,
        1992,
        1989,
        1987,
        1985,
        1983,
        1981,
        1981,
        1983,
        1986,
        1990,
        1994,
        1992,
        1986,
        1982,
        1978,
        1977
      ],
      "cloud_cover_800hPa": [
        0,
        0,
        0,
        0,
        0,
        0,
        0,
        0,
        0,
        0,
        0,
        0,
        0,
        0,
        0,
        0,
        0,
        0,
        0,
        0,
        0,
        0,
        0,
        0,
        0,
        0,
        0,
        0,
        0,
        0,
        0,
        0,
        0,
        0,
        0,
        0,
        0,
        0,
        0,
        0,
        0,
        0,
        0,
        0,
        0,
        0,
        0,
        0
      ],
      "wind_speed_800hPa": [
        18.7,
        18.9,
        18.1,
        17.4,
        15.8,
        13.3,
        12.2,
        10.6,
        9.9,
        9.1,
        7.5,
        6.3,
        2.1,
        1.8,
        3.1,
        3.6,
        3.7,
        3.7,
        3.9,
        3.8,
        3.3,
        2.5,
        2.1,
        1,
        1.2,
        2.2,
        3.4,
        4.5,
        5.5,
        5.4,
        5.1,
        4.9,
        5.4,
        6,
        6,
        6.7,
        8,
        8.7,
        8.7,
        8.9,
        8.7,
        8.3,
        7.5,
        6.3,
        4.9,
        5,
        5.9,
        8.1
      ],
      "wind_direction_800hPa": [
        165,
        163,
        163,
        165,
        166,
        162,
        177,
        173,
        169,
        157,
        142,
        130,
        140,
        63,
        45,
        42,
        36,
        36,
        34,
        60,
        81,
        103,
        113,
        124,
        333,
        330,
        342,
        346,
        351,
        357,
        360,
        360,
        357,
        355,
        350,
        346,
        348,
        351,
        355,
        360,
        7,
        11,
        13,
        10,
        351,
        324,
        313,
        310
      ],
      "temperature_700hPa": [
        16.3,
        16.3,
        16.3,
        16.1,
        16.1,
        16.1,
        16.1,
        16.3,
        16.3,
        16.3,
        16.4,
        16.6,
        16.7,
        16.7,
        16.7,
        17,
        17.2,
        17.2,
        17.7,
        17.7,
        17.8,
        17.8,
        17.8,
        17.5,
        17.5,
        17.5,
        17.3,
        17.3,
        17.3,
        17.5,
        17.7,
        18,
        18.1,
        18.3,
        18.4,
        18.6,
        18.7,
        18.7,
        18.7,
        18.7,
        18.7,
        18.7,
        18.7,
        18.7,
        18.9,
        18.9,
        18.9,
        18.9
      ],
      "relative_humidity_700hPa": [
        21,
        21,
        21,
        22,
        22,
        22,
        23,
        23,
        24,
        24,
        24,
        24,
        23,
        22,
        22,
        22,
        24,
        24,
        26,
        24,
        26,
        26,
        27,
        28,
        28,
        29,
        29,
        29,
        29,
        28,
        27,
        26,
        24,
        24,
        24,
        23,
        23,
        23,
        23,
        24,
        24,
        24,
        24,
        23,
        23,
        23,
        23,
        23
      ],
      "geopotential_height_700hPa": [
        3140,
        3137,
        3141,
        3144,
        3152,
        3153,
        3155,
        3152,
        3153,
        3154,
        3155,
        3152,
        3150,
        3146,
        3147,
        3145,
        3149,
        3152,
        3158,
        3157,
        3153,
        3149,
        3147,
        3145,
        3141,
        3140,
        3143,
        3146,
        3151,
        3154,
        3156,
        3153,
        3150,
        3147,
        3146,
        3144,
        3143,
        3142,
        3142,
        3145,
        3148,
        3153,
        3157,
        3156,
        3150,
        3146,
        3142,
        3140
      ],
      "cloud_cover_700hPa": [
        0,
        0,
        0,
        0,
        0,
        0,
        0,
        0,
        0,
        0,
        0,
        0,
        0,
        0,
        0,
        0,
        0,
        0,
        0,
        0,
        0,
        0,
        0,
        0,
        0,
        0,
        0,
        0,
        0,
        0,
        0,
        0,
        0,
        0,
        0,
        0,
        0,
        0,
        0,
        0,
        0,
        0,
        0,
        0,
        0,
        0,
        0,
        0
      ],
      "wind_speed_700hPa": [
        12.1,
        11.8,
        11.1,
        11,
        11.5,
        14.1,
        12.9,
        13.8,
        13.1,
        12,
        10.5,
        8.9,
        8.5,
        7.7,
        8.1,
        8.6,
        8.6,
        9.5,
        10.3,
        11.5,
        12.4,
        12.4,
        12.2,
        12,
        11.1,
        9.7,
        8.4,
        7,
        6,
        5.1,
        5.1,
        6,
        6.9,
        7.4,
        7.6,
        8.3,
        8.8,
        9.7,
        11.3,
        12.2,
        13.3,
        14,
        13.9,
        12.6,
        11.3,
        10.4,
        9.7,
        8.4
      ],
      "wind_direction_700hPa": [
        152,
        145,
        136,
        128,
        116,
        108,
        115,
        119,
        122,
        126,
        127,
        124,
        99,
        85,
        73,
        77,
        77,
        80,
        77,
        83,
        92,
        103,
        111,
        126,
        125,
        124,
        119,
        115,
        109,
        98,
        82,
        71,
        67,
        60,
        52,
        47,
        43,
        41,
        37,
        37,
        41,
        48,
        53,
        58,
        60,
        61,
        63,
        67
      ]
    }
  }
}